pyfastmath/__init__.py
pyfastmath/_pyfastmath.cp312-win_amd64.pyd
pyfastmath-1.1.2.dist-info/licenses/LICENSE
pyfastmath-1.1.2.dist-info/METADATA
pyfastmath-1.1.2.dist-info/WHEEL
pyfastmath-1.1.2.dist-info/top_level.txt
pyfastmath-1.1.2.dist-info/RECORD
